apogee_connect_rpi/__init__.py
apogee_connect_rpi/main.py
apogee_connect_rpi/version.py
apogee_connect_rpi/Helpers/DefaultConfig.json
apogee_connect_rpi/Helpers/ErrorTracking.json
apogee_connect_rpi/Helpers/reset_bluetooth.sh
apogee_connect_rpi/Scripts/ApogeeUuids.py
apogee_connect_rpi/Scripts/AppConfig.py
apogee_connect_rpi/Scripts/BleScanner.py
apogee_connect_rpi/Scripts/Calculators.py
apogee_connect_rpi/Scripts/CollectionManager.py
apogee_connect_rpi/Scripts/CommandImplement.py
apogee_connect_rpi/Scripts/CronManager.py
apogee_connect_rpi/Scripts/CsvManager.py
apogee_connect_rpi/Scripts/DiagnosticZipGenerator.py
apogee_connect_rpi/Scripts/ErrorHandling.py
apogee_connect_rpi/Scripts/SensorClasses.py
apogee_connect_rpi/Scripts/SensorManager.py
apogee_connect_rpi/Scripts/liveDataTypes.py
apogee_connect_rpi-1.1.6.dist-info/licenses/LICENSE
apogee_connect_rpi-1.1.6.dist-info/METADATA
apogee_connect_rpi-1.1.6.dist-info/WHEEL
apogee_connect_rpi-1.1.6.dist-info/entry_points.txt
apogee_connect_rpi-1.1.6.dist-info/top_level.txt
apogee_connect_rpi-1.1.6.dist-info/RECORD
