Metadata-Version: 2.4
Name: apogee-connect-rpi
Version: 1.1.6
Summary: Automates data collection with Bluetooth sensors from Apogee Instruments, Inc. using a Raspberry Pi
Author-email: "Apogee Instruments, Inc." <developer@apogeeinstruments.com>
License: MIT License
Classifier: Development Status :: 5 - Production/Stable
Classifier: Intended Audience :: Science/Research
Classifier: Programming Language :: Python :: 3
Classifier: License :: OSI Approved :: MIT License
Classifier: Operating System :: POSIX :: Linux
Classifier: Topic :: Scientific/Engineering
Classifier: Topic :: Scientific/Engineering :: Information Analysis
Requires-Python: >=3.7
License-File: LICENSE
Requires-Dist: numpy
Requires-Dist: python-crontab
Requires-Dist: bleak
Requires-Dist: asyncio
Requires-Dist: filelock
Requires-Dist: packaging
Requires-Dist: requests
Requires-Dist: python-dateutil
Dynamic: license-file
